[
  {
    "name": "Federer",
    "size": 81
  },
  {
    "name": "Nadal",
    "size": 79
  },
  {
    "name": "Roddick",
    "size": 59
  },
  {
    "name": "Ljubicic",
    "size": 57
  },
  {
    "name": "Gaudio",
    "size": 56
  },
  {
    "name": "Davydenko",
    "size": 56
  },
  {
    "name": "Coria",
    "size": 55
  },
  {
    "name": "Gonzalez",
    "size": 50
  },
  {
    "name": "Johansson",
    "size": 47
  },
  {
    "name": "Carlos",
    "size": 46
  },
  {
    "name": "Stepanek",
    "size": 45
  },
  {
    "name": "Nalbandian",
    "size": 44
  },
  {
    "name": "Ancic",
    "size": 44
  },
  {
    "name": "Robredo",
    "size": 43
  },
  {
    "name": "Ferrer",
    "size": 43
  }
]